pymolecule_parser/__about__.py
pymolecule_parser/__init__.py
pymolecule_parser/pymolecule_parser.py
pymolecule_parser-0.1.0.dist-info/METADATA
pymolecule_parser-0.1.0.dist-info/WHEEL
pymolecule_parser-0.1.0.dist-info/licenses/LICENSE
pymolecule_parser-0.1.0.dist-info/RECORD
