Metadata-Version: 2.1
Name: pymolecule-parser
Version: 0.1.0
Summary: A parser for molecule formula. Nested brackets are supported.
Project-URL: Documentation, https://github.com/kohei-noda-qcrg/pymolecule-parser#readme
Project-URL: Issues, https://github.com/kohei-noda-qcrg/pymolecule-parser/issues
Project-URL: Source, https://github.com/kohei-noda-qcrg/pymolecule-parser
Author-email: Kohei Noda <kohei-noda@hiroshima-u.ac.jp>
License-Expression: MIT
License-File: LICENSE
Classifier: Development Status :: 4 - Beta
Classifier: Programming Language :: Python
Classifier: Programming Language :: Python :: 3.7
Classifier: Programming Language :: Python :: 3.8
Classifier: Programming Language :: Python :: 3.9
Classifier: Programming Language :: Python :: 3.10
Classifier: Programming Language :: Python :: 3.11
Classifier: Programming Language :: Python :: Implementation :: CPython
Classifier: Programming Language :: Python :: Implementation :: PyPy
Requires-Python: >=3.7
